aylak/__init__.py
aylak/__main__.py
aylak/sync.py
aylak/colors/__init__.py
aylak/colors/_print.py
aylak/colors/art.py
aylak/colors/handler.py
aylak/colors/hex.py
aylak/colors/rgb.py
aylak/colors/utils.py
aylak/exceptions/__init__.py
aylak/exceptions/erros.py
aylak/exceptions/colors/__init__.py
aylak/exceptions/colors/exceptions.py
aylak/exceptions/voice/__init__.py
aylak/exceptions/voice/exceptions.py
aylak/image/__init__.py
aylak/image/imagetool.py
aylak/rich/__init__.py
aylak/rich/__main__.py
aylak/rich/_cell_widths.py
aylak/rich/_export_format.py
aylak/rich/_extension.py
aylak/rich/_fileno.py
aylak/rich/_inspect.py
aylak/rich/_log_render.py
aylak/rich/_loop.py
aylak/rich/_null_file.py
aylak/rich/_palettes.py
aylak/rich/_pick.py
aylak/rich/_ratio.py
aylak/rich/_spinners.py
aylak/rich/_stack.py
aylak/rich/_timer.py
aylak/rich/_win32_console.py
aylak/rich/_windows.py
aylak/rich/_windows_renderer.py
aylak/rich/_wrap.py
aylak/rich/abc.py
aylak/rich/align.py
aylak/rich/ansi.py
aylak/rich/bar.py
aylak/rich/box.py
aylak/rich/cells.py
aylak/rich/color.py
aylak/rich/color_triplet.py
aylak/rich/columns.py
aylak/rich/console.py
aylak/rich/constrain.py
aylak/rich/containers.py
aylak/rich/control.py
aylak/rich/default_styles.py
aylak/rich/diagnose.py
aylak/rich/emoji.py
aylak/rich/errors.py
aylak/rich/file_proxy.py
aylak/rich/filesize.py
aylak/rich/highlighter.py
aylak/rich/json.py
aylak/rich/jupyter.py
aylak/rich/layout.py
aylak/rich/live.py
aylak/rich/live_render.py
aylak/rich/logging.py
aylak/rich/markdown.py
aylak/rich/markup.py
aylak/rich/measure.py
aylak/rich/padding.py
aylak/rich/pager.py
aylak/rich/palette.py
aylak/rich/panel.py
aylak/rich/pretty.py
aylak/rich/progress.py
aylak/rich/progress_bar.py
aylak/rich/prompt.py
aylak/rich/protocol.py
aylak/rich/py.typed
aylak/rich/region.py
aylak/rich/repr.py
aylak/rich/rule.py
aylak/rich/scope.py
aylak/rich/screen.py
aylak/rich/segment.py
aylak/rich/spinner.py
aylak/rich/status.py
aylak/rich/style.py
aylak/rich/styled.py
aylak-1.0.0.3.dist-info/METADATA
aylak-1.0.0.3.dist-info/WHEEL
aylak-1.0.0.3.dist-info/dependency_links.txt
aylak-1.0.0.3.dist-info/entry_points.txt
aylak-1.0.0.3.dist-info/top_level.txt
aylak-1.0.0.3.dist-info/RECORD
